nsefeed/__init__.py
nsefeed/cache.py
nsefeed/config.py
nsefeed/constants.py
nsefeed/exceptions.py
nsefeed/logger.py
nsefeed/py.typed
nsefeed/session.py
nsefeed/ticker.py
nsefeed/utils.py
nsefeed/derivatives/__init__.py
nsefeed/derivatives/derivative_data.py
nsefeed/derivatives/get_func.py
nsefeed/equity/__init__.py
nsefeed/equity/equity_data.py
nsefeed/equity/get_func.py
nsefeed/indices/__init__.py
nsefeed/indices/config.py
nsefeed/indices/index_data.py
nsefeed/scrapers/__init__.py
nsefeed/scrapers/bhav_copy.py
nsefeed-1.0.2.dist-info/licenses/LICENSE
nsefeed-1.0.2.dist-info/METADATA
nsefeed-1.0.2.dist-info/WHEEL
nsefeed-1.0.2.dist-info/top_level.txt
nsefeed-1.0.2.dist-info/RECORD
