Metadata-Version: 2.4
Name: nsefeed
Version: 1.0.2
Summary: Minimal python library for ingesting historical NSE India data - Indices, Equity, and Derivatives with yfinance-style API
Author-email: Shubham Nayak <shubhamnayaksn1708@gmail.com>
Maintainer-email: Shubham Nayak <shubhamnayaksn1708@gmail.com>
License: Apache-2.0
Project-URL: Homepage, https://github.com/shubhamnayak1708/nsefeed
Project-URL: Documentation, https://github.com/shubhamnayak1708/nsefeed#readme
Project-URL: Repository, https://github.com/shubhamnayak1708/nsefeed.git
Project-URL: Issues, https://github.com/shubhamnayak1708/nsefeed/issues
Project-URL: Changelog, https://github.com/shubhamnayak1708/nsefeed/blob/main/CHANGELOG.md
Keywords: nse,nseindia,stock,market,finance,india,trading,stocks,equities,nifty,sensex,bhavcopy,ohlc,historical-data,derivatives,options,futures,capital-market,yfinance,data-ingestion,market-data,financial-data
Classifier: Development Status :: 5 - Production/Stable
Classifier: Intended Audience :: Developers
Classifier: Intended Audience :: Financial and Insurance Industry
Classifier: License :: OSI Approved :: Apache Software License
Classifier: Operating System :: OS Independent
Classifier: Programming Language :: Python :: 3
Classifier: Programming Language :: Python :: 3.9
Classifier: Programming Language :: Python :: 3.10
Classifier: Programming Language :: Python :: 3.11
Classifier: Programming Language :: Python :: 3.12
Classifier: Topic :: Office/Business :: Financial :: Investment
Classifier: Topic :: Software Development :: Libraries :: Python Modules
Classifier: Typing :: Typed
Requires-Python: >=3.9
License-File: LICENSE
Requires-Dist: requests>=2.28.0
Requires-Dist: pandas>=1.5.0
Requires-Dist: python-dateutil>=2.8.0
Provides-Extra: dev
Requires-Dist: black>=23.0.0; extra == "dev"
Requires-Dist: isort>=5.12.0; extra == "dev"
Requires-Dist: mypy>=1.0.0; extra == "dev"
Requires-Dist: pylint>=2.17.0; extra == "dev"
Provides-Extra: all
Requires-Dist: nsefeed[dev]; extra == "all"
Dynamic: license-file
